easy_multiprocess/__init__.py
easy_multiprocess/easy_multiprocess.py
easy_multiprocess-1.0.1.dist-info/LICENSE
easy_multiprocess-1.0.1.dist-info/METADATA
easy_multiprocess-1.0.1.dist-info/WHEEL
easy_multiprocess-1.0.1.dist-info/top_level.txt
easy_multiprocess-1.0.1.dist-info/RECORD
