Metadata-Version: 2.1
Name: easy_multiprocess
Version: 1.0.1
Summary: Use all your cores with no extra code
Author: Pranay
License: MIT License
Classifier: Programming Language :: Python :: 3
Classifier: License :: OSI Approved :: MIT License
Classifier: Operating System :: OS Independent
License-File: LICENSE
